MANIFEST.in
setup.cfg
setup.py
puzcw/__init__.py
puzcw/box.py
puzcw/clues.py
puzcw/crossword.py
puzcw/exception.py
puzcw/image.py
puzcw.egg-info/PKG-INFO
puzcw.egg-info/SOURCES.txt
puzcw.egg-info/dependency_links.txt
puzcw.egg-info/requires.txt
puzcw.egg-info/top_level.txt
puzcw/static/FreeSans.ttf