Metadata-Version: 1.0
Name: puzcw
Version: 0.0.12
Summary: Python API for converting puz files to python objects
Home-page: https://github.com/bwu/puzcw
Author: Brian Wu
Author-email: brian.george.wu@gmail.com
License: UNKNOWN
Keywords: crossword,puz
Platform: UNKNOWN
